[
  {
    "date": "2026-07-04",
    "question": "孩子视力下降，九合一油也一直在喝，是否需要补充其他的？",
    "answer": "黄老师：基础全营养素，VC泡腾粉，胶原蛋白肽，三丁酸甘油酯打底，加九合一油，R硫辛酸钠胶囊，NAC胶囊，甘氨酸，烟酸，无水甜菜碱，复合活性B族胶囊，B2胶囊。多晒太阳，多户外活动，眺望远处。改变饮食，最少低碳——生酮——纯肉。",
    "type": "Q&A",
    "symptoms": [
      "视力下降"
    ],
    "supplements": [
      "基础全营养素",
      "维C泡腾粉",
      "胶原蛋白肽",
      "三丁酸甘油酯",
      "九合一油",
      "硫辛酸",
      "NAC",
      "甘氨酸",
      "烟酸",
      "无水甜菜碱",
      "活性B族",
      "维生素B2"
    ],
    "topics_system": [
      "运动五官与结缔组织",
      "饮食结构与膳食模式"
    ],
    "topic_group": "孩子健康",
    "source_file": "2026年07月04日_baoer.md",
    "id": "2026-07-04-01"
  },
  {
    "date": "2026-07-04",
    "question": "那些便秘的能不能直接用VC冲肠？",
    "answer": "黄老师：可以，但是不能太频繁，肠道黏膜一直被冲掉，恢复来不及，对肠道不好。",
    "type": "Q&A",
    "symptoms": [
      "便秘"
    ],
    "supplements": [
      "维生素C"
    ],
    "topics_system": [
      "屏障消化与肠道"
    ],
    "topic_group": "补剂用法与搭配",
    "source_file": "2026年07月04日_baoer.md",
    "id": "2026-07-04-02"
  },
  {
    "date": "2026-07-04",
    "question": "做了切胃手术，还是190斤，且吃非常少，热量平衡理论失效？",
    "answer": "黄老师：没失效，是因为甲减了，代谢下降了30%到50%。",
    "type": "Q&A",
    "symptoms": [
      "肥胖"
    ],
    "supplements": [],
    "topics_system": [
      "能量线粒体与代谢",
      "内分泌与激素调控"
    ],
    "topic_group": "代谢与体重管理",
    "source_file": "2026年07月04日_baoer.md",
    "id": "2026-07-04-03"
  },
  {
    "date": "2026-07-04",
    "question": "有氧激活AMPK，为什么很多长跑运动员看起来更老？",
    "answer": "黄老师：自由基过多。",
    "type": "Q&A",
    "symptoms": [],
    "supplements": [],
    "topics_system": [
      "氧化还原与抗氧化防御",
      "运动五官与结缔组织"
    ],
    "topic_group": "运动与氧化",
    "source_file": "2026年07月04日_baoer.md",
    "id": "2026-07-04-04"
  },
  {
    "date": "2026-07-04",
    "question": "生酮后总早醒，是不是不适合生酮？",
    "answer": "黄老师：把盐吃够，每天最少10克盐。",
    "type": "Q&A",
    "symptoms": [
      "失眠"
    ],
    "supplements": [
      "海盐"
    ],
    "topics_system": [
      "神经睡眠与脑雾",
      "饮食结构与膳食模式"
    ],
    "topic_group": "生酮适应",
    "dosage_info": [
      {
        "supplement": "海盐",
        "dosage": "每天最少10克盐",
        "timing": "日常补充"
      }
    ],
    "source_file": "2026年07月04日_baoer.md",
    "id": "2026-07-04-05"
  },
  {
    "date": "2026-07-04",
    "question": "白天忙起来可以不睡，无聊就会睡，就是没劲。",
    "answer": "黄老师：把盐吃够。",
    "type": "Q&A",
    "symptoms": [
      "乏力"
    ],
    "supplements": [
      "海盐"
    ],
    "topics_system": [
      "能量线粒体与代谢"
    ],
    "topic_group": "盐与电解质",
    "source_file": "2026年07月04日_baoer.md",
    "id": "2026-07-04-06"
  },
  {
    "date": "2026-07-04",
    "question": "娃游泳呛水了，喝些VC泡腾可以么？",
    "answer": "黄老师：可以吃。不只是维C，其他营养素都可以吃。",
    "type": "Q&A",
    "symptoms": [],
    "supplements": [
      "维生素C"
    ],
    "topics_system": [
      "免疫自免与过敏"
    ],
    "topic_group": "儿童健康",
    "source_file": "2026年07月04日_baoer.md",
    "id": "2026-07-04-07"
  },
  {
    "date": "2026-07-04",
    "question": "今天盐加上了口渴呢？",
    "answer": "黄老师：钾也跟上，一般建议10克盐，2000毫克钾离子，五六百毫克镁离子。你可以先换成低钠盐，里面有一些钾，不至于钾太低。没有抗结剂和防腐剂的盐就行。",
    "type": "Q&A",
    "symptoms": [
      "口干"
    ],
    "supplements": [
      "海盐",
      "钾",
      "镁"
    ],
    "topics_system": [
      "血管血液与微循环"
    ],
    "topic_group": "盐与电解质",
    "dosage_info": [
      {
        "supplement": "海盐",
        "dosage": "10克/天",
        "timing": ""
      },
      {
        "supplement": "钾",
        "dosage": "2000毫克钾离子/天",
        "timing": ""
      },
      {
        "supplement": "镁",
        "dosage": "五六百毫克镁离子/天",
        "timing": ""
      }
    ],
    "source_file": "2026年07月04日_baoer.md",
    "id": "2026-07-04-08"
  },
  {
    "date": "2026-07-04",
    "question": "二手烟怎么排？",
    "answer": "黄老师：吃补剂，抵抗伤害，基本上只要吃基础全营养素和VC泡腾粉就行了。",
    "type": "Q&A",
    "symptoms": [],
    "supplements": [
      "基础全营养素",
      "维C泡腾粉"
    ],
    "topics_system": [
      "解毒肝肾与排毒"
    ],
    "topic_group": "排毒",
    "source_file": "2026年07月04日_baoer.md",
    "id": "2026-07-04-09"
  },
  {
    "date": "2026-07-04",
    "question": "肉吃多，痰也多，怎么办？",
    "answer": "黄老师：吃肉痰多，说明你还没有适应。吃的蛋白质多了，呼吸道粘膜有更好的战斗力把炎症打扫出去。这时候更应该多吃肉、多喝肉汤，帮助你排出不好的物质。",
    "type": "Q&A",
    "symptoms": [],
    "supplements": [],
    "topics_system": [
      "饮食结构与膳食模式",
      "免疫自免与过敏"
    ],
    "topic_group": "饮食适应",
    "source_file": "2026年07月04日_baoer.md",
    "id": "2026-07-04-10"
  },
  {
    "date": "2026-07-04",
    "question": "【群友分享】西红柿拉肚子",
    "answer": "群友：不知道是不是今天吃了3个生的西红柿的缘故，竟然拉肚子了。黄老师评：西红柿是茄科，含有茄碱之类的东西。我的建议是最好煮熟。",
    "type": "群友反馈",
    "symptoms": [
      "腹泻"
    ],
    "supplements": [],
    "topics_system": [
      "屏障消化与肠道",
      "饮食结构与膳食模式"
    ],
    "topic_group": "食物不耐受",
    "source_file": "2026年07月04日_baoer.md",
    "id": "2026-07-04-11"
  },
  {
    "date": "2026-07-04",
    "question": "40岁以上抗衰推荐哪些补剂？",
    "answer": "问：40岁以上抗衰推荐哪些补剂呢？目前口服服用的有胶原蛋白肽、透明质酸钠、抗衰胶囊、维生素C、基础全营养素、NAC。黄老师：可以加个三丁酸甘油酯。更加具体可以私信我。追问：抗氧化美白对应的是哪个补剂呢？黄老师：这个东西不是单独的，是一个全面的综合来看的。",
    "type": "Q&A",
    "symptoms": [],
    "supplements": [
      "胶原蛋白肽",
      "透明质酸钠",
      "抗衰定制营养素",
      "维生素C",
      "基础全营养素",
      "NAC",
      "三丁酸甘油酯"
    ],
    "topics_system": [
      "氧化还原与抗氧化防御",
      "运动五官与结缔组织"
    ],
    "topic_group": "抗衰老",
    "source_file": "2026年07月04日_baoer.md",
    "id": "2026-07-04-12"
  },
  {
    "date": "2026-07-04",
    "question": "猪肉的肥肉少吃？猪油还能吃吗？",
    "answer": "黄老师：轮换吃就好，不用紧张，再差也比种子油好。",
    "type": "Q&A",
    "symptoms": [],
    "supplements": [],
    "topics_system": [
      "饮食结构与膳食模式"
    ],
    "topic_group": "饮食结构与油脂选择",
    "source_file": "2026年07月04日_baoer.md",
    "id": "2026-07-04-13"
  },
  {
    "date": "2026-07-04",
    "question": "猪油欧米伽六含量比一些植物油都高？",
    "answer": "黄老师：这是小概率事件。",
    "type": "Q&A",
    "symptoms": [],
    "supplements": [],
    "topics_system": [
      "饮食结构与膳食模式"
    ],
    "topic_group": "饮食结构与油脂选择",
    "source_file": "2026年07月04日_baoer.md",
    "id": "2026-07-04-14"
  },
  {
    "date": "2026-07-04",
    "question": "睡前能吃东西吗？",
    "answer": "黄老师：你可以试试，睡眠没影响就行。",
    "type": "Q&A",
    "symptoms": [],
    "supplements": [],
    "topics_system": [
      "饮食结构与膳食模式"
    ],
    "topic_group": "饮食习惯",
    "source_file": "2026年07月04日_baoer.md",
    "id": "2026-07-04-15"
  },
  {
    "date": "2026-07-04",
    "question": "生酮和纯肉的时候，可以吃生可可粉嘛？",
    "answer": "黄老师：尽量少吃，可可粉是种子，有植物毒素，如果不是新鲜的，放一段时间还可能有霉菌毒素超标的问题。可可又苦，你尝不出来它是不是已经变质。偶尔吃点没事，比如巧克力，但不建议经常吃、天天吃。追问：看来只要是植物就不能碰？黄老师：是少碰，特别是严格修复肠漏期间的人尽量别碰，健康人不用太严格。",
    "type": "Q&A",
    "symptoms": [],
    "supplements": [],
    "topics_system": [
      "饮食结构与膳食模式"
    ],
    "topic_group": "饮食结构与油脂选择",
    "source_file": "2026年07月04日_baoer.md",
    "id": "2026-07-04-16"
  },
  {
    "date": "2026-07-04",
    "question": "网上说甘氨酸不能跟牛磺酸一起，会冲突，是吗？",
    "answer": "黄老师：不会，早就辟谣了。",
    "type": "Q&A",
    "symptoms": [],
    "supplements": [
      "甘氨酸",
      "牛磺酸"
    ],
    "topics_system": [
      "氧化还原与抗氧化防御"
    ],
    "topic_group": "补剂用法与搭配",
    "source_file": "2026年07月04日_baoer.md",
    "id": "2026-07-04-17"
  },
  {
    "date": "2026-07-04",
    "question": "猪皮85度慢煮24小时能释放胶原蛋白肽么？",
    "answer": "黄老师：可以。",
    "type": "Q&A",
    "symptoms": [],
    "supplements": [
      "胶原蛋白肽"
    ],
    "topics_system": [
      "运动五官与结缔组织"
    ],
    "topic_group": "胶原蛋白",
    "source_file": "2026年07月04日_baoer.md",
    "id": "2026-07-04-18"
  },
  {
    "date": "2026-07-04",
    "question": "炖牛月牙骨、炖猪皮和野兽生活10克胶原蛋白肽哪个好？",
    "answer": "黄老师：牛月牙骨没有定量，不好比较。另外这两个不冲突，可以结合在一起。还有一个重要因素，就是它们不完全重叠。炖的牛羊骨汤里面，有相当一部分东西是用来滋养肠道的。胶原蛋白肽产品，主要就是吸收到体内的。",
    "type": "Q&A",
    "symptoms": [],
    "supplements": [
      "胶原蛋白肽",
      "牛骨汤"
    ],
    "topics_system": [
      "运动五官与结缔组织",
      "屏障消化与肠道"
    ],
    "topic_group": "胶原蛋白",
    "source_file": "2026年07月04日_baoer.md",
    "id": "2026-07-04-19"
  },
  {
    "date": "2026-07-04",
    "question": "脂溶性维C有什么说法吗？",
    "answer": "黄老师：脂溶性维C没啥用，脂质体维C才有用。",
    "type": "Q&A",
    "symptoms": [],
    "supplements": [
      "维生素C",
      "脂质体维生素C"
    ],
    "topics_system": [
      "氧化还原与抗氧化防御"
    ],
    "topic_group": "补剂用法与搭配",
    "source_file": "2026年07月04日_baoer.md",
    "id": "2026-07-04-20"
  },
  {
    "date": "2026-07-04",
    "question": "【群友分享】补剂比药都灵",
    "answer": "群友：补剂确实比药都灵，且没有副作用，我有时真的有点恍惚，难道营养素里有西药？当然这是夸的另一种说法。黄老师答：只要明白根本原因是什么。生病之后的恢复并不是靠药，而是靠自身的各种功能，主要是免疫功能。这些运行需要能量和营养。全面足量、足够大的剂量在生病的时候补充才会有用，是因为它从根本上支持了身体修复治愈的能力，就这么简单。药是通过抑制细胞功能发挥作用，它不止不支持细胞修复，还在抑制某些细胞功能，让指标变得好看，但不解决根本问题。",
    "type": "群友反馈",
    "symptoms": [],
    "supplements": [],
    "topics_system": [
      "免疫自免与过敏"
    ],
    "topic_group": "营养观念",
    "source_file": "2026年07月04日_baoer.md",
    "id": "2026-07-04-21"
  },
  {
    "date": "2026-07-04",
    "question": "【群友分享】好的复维很少",
    "answer": "群友：好的复维很少，宁哥的复维就相当厉害，成分含量还有配比。网上一些博主推的复维，一堆含有不少氧化物和非活性的，真的不行。",
    "type": "群友反馈",
    "symptoms": [],
    "supplements": [],
    "topics_system": [
      "其他/综合"
    ],
    "topic_group": "补剂选择",
    "source_file": "2026年07月04日_baoer.md",
    "id": "2026-07-04-22"
  },
  {
    "date": "2026-07-04",
    "question": "大剂量碘怎么补？想从350微克吃到10毫克左右。",
    "answer": "黄老师：那不需要卢戈尔碘液。基础全营养素你能吃够4包的话，应该有6毫克的碘。再加一粒微量元素胶囊，应该有3毫克的碘，基本上接近10毫克。如果你想要更多，十几毫克甚至几十毫克，考虑去买碘化钾，但要买进口防辐射的，不然剂量会很低。",
    "type": "Q&A",
    "symptoms": [],
    "supplements": [
      "碘",
      "碘化钾",
      "基础全营养素",
      "定制微量元素营养素"
    ],
    "topics_system": [
      "解毒肝肾与排毒",
      "内分泌与激素调控"
    ],
    "topic_group": "碘补充",
    "dosage_info": [
      {
        "supplement": "碘",
        "dosage": "基础全营养素4包约6毫克碘+微量元素胶囊1粒约3毫克碘，合计约10毫克",
        "timing": ""
      },
      {
        "supplement": "碘化钾",
        "dosage": "十几毫克到几十毫克",
        "timing": ""
      }
    ],
    "source_file": "2026年07月04日_baoer.md",
    "id": "2026-07-04-23"
  },
  {
    "date": "2026-07-04",
    "question": "B族与小黄冲突吗？2粒小黄+1粒活性B族可以吗？",
    "answer": "黄老师：不冲突，可以2粒小黄+2粒复合活性B族胶囊。",
    "type": "Q&A",
    "symptoms": [],
    "supplements": [
      "活性B族",
      "小黄"
    ],
    "topics_system": [
      "能量线粒体与代谢"
    ],
    "topic_group": "补剂用法与搭配",
    "dosage_info": [
      {
        "supplement": "小黄",
        "dosage": "2粒",
        "timing": ""
      },
      {
        "supplement": "活性B族",
        "dosage": "2粒复合活性B族胶囊",
        "timing": ""
      }
    ],
    "source_file": "2026年07月04日_baoer.md",
    "id": "2026-07-04-24"
  },
  {
    "date": "2026-07-04",
    "question": "包埋啥意思，就是脂质体？",
    "answer": "黄老师：对，市面上脂质体很多包埋率都堪忧。没有关系，自己做。教程（[自制脂质体教程](https://mp.weixin.qq.com/s/-yTmPAjM1Dun62hIyCR_mA)）。这个做出来比绝大多数脂质体都靠谱。追问：这样做等于所有营养元素都可以缓释？黄老师：不是简单的缓释，是尽量把营养素都包埋，尽量把尽可能多的营养素进行脂质体化。如果你加的营养粉比较多，卵磷脂没有那么多的话，不可能都包埋得完。只想单纯包埋维C，可以10克维C加30克卵磷脂，按照步骤做就行了，包埋率挺高的。",
    "type": "Q&A",
    "symptoms": [],
    "supplements": [
      "卵磷脂",
      "维生素C",
      "脂质体维生素C"
    ],
    "topics_system": [
      "氧化还原与抗氧化防御"
    ],
    "topic_group": "补剂用法与搭配",
    "dosage_info": [
      {
        "supplement": "卵磷脂",
        "dosage": "30克卵磷脂+10克维C做包埋",
        "timing": ""
      }
    ],
    "source_file": "2026年07月04日_baoer.md",
    "id": "2026-07-04-25"
  },
  {
    "date": "2026-07-04",
    "question": "甘氨酸、胶原蛋白肽，是不是也应该算入每天的蛋白质摄入总量中？",
    "answer": "黄老师：不算。",
    "type": "Q&A",
    "symptoms": [],
    "supplements": [
      "甘氨酸",
      "胶原蛋白肽"
    ],
    "topics_system": [
      "运动五官与结缔组织",
      "饮食结构与膳食模式"
    ],
    "topic_group": "胶原蛋白",
    "source_file": "2026年07月04日_baoer.md",
    "id": "2026-07-04-26"
  },
  {
    "date": "2026-07-04",
    "question": "怎么去区分自己吃的补剂是植物化合物补剂？",
    "answer": "黄老师：只要不是正分子营养的，基本上都是植物化合物补剂。最经典的就是姜黄素、白藜芦醇之类的。你看成分就知道是不是正分子还是植物化合物。",
    "type": "Q&A",
    "symptoms": [],
    "supplements": [],
    "topics_system": [
      "其他/综合"
    ],
    "topic_group": "补剂认知",
    "source_file": "2026年07月04日_baoer.md",
    "id": "2026-07-04-27"
  },
  {
    "date": "2026-07-04",
    "question": "吃过很多肝脏后，当天还要不要吃基础全营养素？",
    "answer": "黄老师：我是正常吃，不会中毒，因为里面锌铜也很高，所以不怕VA高。",
    "type": "Q&A",
    "symptoms": [],
    "supplements": [
      "基础全营养素",
      "牛肝"
    ],
    "topics_system": [
      "解毒肝肾与排毒"
    ],
    "topic_group": "饮食结构与营养认知",
    "source_file": "2026年07月04日_baoer.md",
    "id": "2026-07-04-28"
  },
  {
    "date": "2026-07-04",
    "question": "为什么一直强调胶原蛋白肽，和普通蛋白质的多肽有什么区别？",
    "answer": "黄老师：成分不一样。普通蛋白质是全谱氨基酸，胶原蛋白不是全谱蛋白质。",
    "type": "Q&A",
    "symptoms": [],
    "supplements": [
      "胶原蛋白肽"
    ],
    "topics_system": [
      "运动五官与结缔组织"
    ],
    "topic_group": "胶原蛋白",
    "source_file": "2026年07月04日_baoer.md",
    "id": "2026-07-04-29"
  },
  {
    "date": "2026-07-04",
    "question": "多长时间算是有效有氧？",
    "answer": "黄老师：30到40分钟中等强度就行，而且不要每天跑。",
    "type": "Q&A",
    "symptoms": [],
    "supplements": [],
    "topics_system": [
      "运动五官与结缔组织",
      "能量线粒体与代谢"
    ],
    "topic_group": "运动与健康",
    "source_file": "2026年07月04日_baoer.md",
    "id": "2026-07-04-30"
  },
  {
    "date": "2026-07-04",
    "question": "【群友分享】营养与药物的认知",
    "answer": "群友：我发现一些认知低的妈妈，孩子一点小头痛发热，就头孢、快克（对乙酰氨基酚）、布洛芬、蒲地蓝、含罂粟麻黄碱的止咳糖浆等等，明确的毒物往小孩嘴里灌。但是让她们平时给小孩吃点维生素D、维生素C、镁片，或者鱼油、叶黄素玉米黄质之类的，天天怀疑这样怀疑那样。黄老师评：对于营养的认识太浅薄了，对于药物的副作用认识也是太浅薄了。吃药那么毒都不怕，吃点正分子营养素却担惊受怕。",
    "type": "群友反馈",
    "symptoms": [],
    "supplements": [],
    "topics_system": [
      "免疫自免与过敏",
      "其他/综合"
    ],
    "topic_group": "营养观念",
    "source_file": "2026年07月04日_baoer.md",
    "id": "2026-07-04-31"
  },
  {
    "date": "2026-07-04",
    "question": "【群友分享】生酮的乌龟",
    "answer": "群友：我发小给他家乌龟生酮，只喂虾，从小到大一次病没生过，身体状态特好，精力旺盛，指甲长，龟掌肉质更紧实。同品种，我家乌龟吃龟粮，长得肥头大耳，很臃肿，爱睡觉，还偶尔生病。",
    "type": "群友反馈",
    "symptoms": [],
    "supplements": [],
    "topics_system": [
      "饮食结构与膳食模式"
    ],
    "topic_group": "生酮饮食",
    "source_file": "2026年07月04日_baoer.md",
    "id": "2026-07-04-32"
  },
  {
    "date": "2026-07-04",
    "question": "现代医疗中营养的重要性",
    "answer": "黄老师分享：4.12 复制打开抖音，查看【瘦龙的生物黑客朋友们的作品】[听医学博士说说现代医疗中，营养的重要性](https://v.douyin.com/Gxlczh_HMKc/)",
    "type": "Q&A",
    "symptoms": [],
    "supplements": [],
    "topics_system": [
      "其他/综合"
    ],
    "topic_group": "营养观念",
    "source_file": "2026年07月04日_baoer.md",
    "id": "2026-07-04-33"
  },
  {
    "date": "2026-07-04",
    "question": "血钙高根本不是维生素D中毒",
    "answer": "黄老师分享：一、常规补充维生素D不会导致血钙升高。维生素D只是促进肠道钙吸收，且吸收率在血药浓度达到32 ng/mL后就趋于饱和。每天1万IU连吃16周，血药浓度翻4倍，血钙几乎不变。二、真正的维生素D中毒，剂量远高于日常补充。中毒案例累计摄入量在360万到2.1亿IU，血药浓度需超过150 ng/mL。中毒机制不是\"吸钙太多\"，而是超高剂量直接从骨骼\"抽钙\"入血。三、单次血钙偏高，大概率是测量误差。止血带勒太久、喝水多少、蛋白波动都会影响读数。正规流程是必须多次复查确认，一次偏高不算数。四、持续血钙升高，问题不在维生素D，而在甲状旁腺。头号原因是原发性甲状旁腺功能亢进（PHPT），绝经后女性中约1/20到1/50患病，漏诊率高达60%到80%。甲状旁腺上的小腺瘤不受控分泌PTH，导致血钙持续偏高。补充维生素D只是\"提前暴露\"了这个潜在问题。五、实操建议：补充维生素D期间，定期监测三项指标——脂溶性维生素ADEK、血清电解质（钙、镁、磷）、甲状旁腺素（PTH）。判断逻辑：血钙升高时，PTH应当被压低；如果PTH仍在正常范围甚至偏高，基本可以判定是甲状旁腺出了问题，而非维生素D中毒。",
    "type": "Q&A",
    "symptoms": [],
    "supplements": [
      "维生素D"
    ],
    "topics_system": [
      "内分泌与激素调控"
    ],
    "clinical_indicators": [
      "血清钙",
      "甲状旁腺素",
      "25-羟基维生素D"
    ],
    "topic_group": "维生素D",
    "source_file": "2026年07月04日_baoer.md",
    "id": "2026-07-04-34"
  },
  {
    "date": "2026-07-04",
    "question": "【群友见证】拔牙后使用VC",
    "answer": "群友：我老公因为拔牙后炎症导致口腔肿得像鸡蛋，还引发了感冒，鼻涕喷嚏不停，牙医说消炎药不够劲要去医院挂水。我没听，回家让他每天服用10到15克的VC，一整天不间断服用。第二天消肿一半，第三天感冒和肿胀全都消失了，今天还有点小鼻涕。",
    "type": "群友反馈",
    "symptoms": [
      "炎症"
    ],
    "supplements": [
      "维生素C"
    ],
    "topics_system": [
      "免疫自免与过敏",
      "运动五官与结缔组织"
    ],
    "topic_group": "维生素C实践",
    "dosage_info": [
      {
        "supplement": "维生素C",
        "dosage": "每天10到15克",
        "timing": "一整天不间断服用"
      }
    ],
    "source_file": "2026年07月04日_baoer.md",
    "id": "2026-07-04-35"
  },
  {
    "date": "2026-07-04",
    "question": "【群友分享】基础营养素的使用",
    "answer": "群友：这个营养素感觉好像已经有点作用，我做了这么久车竟然一点都不累。群友评：刚开始吃的话，因为有对比，效果可能更明显一点。可能心理作用占一部分，实际效果也占一部分。",
    "type": "横向互助",
    "symptoms": [],
    "supplements": [
      "基础全营养素"
    ],
    "topics_system": [
      "能量线粒体与代谢"
    ],
    "topic_group": "补剂体验",
    "source_file": "2026年07月04日_baoer.md",
    "id": "2026-07-04-36"
  },
  {
    "date": "2026-07-04",
    "question": "【群友分享】猪肥肉",
    "answer": "群友：猪肥肉真的很香，和牛羊的奶香不一样的风味。以前吃不下肥猪肉，现在觉得怎么这么好吃，库库全炫了。群友：我也是以前不爱吃肥肉要yue的那种，现在却成了心头好，纯肉后肠道菌群迅速调整。",
    "type": "横向互助",
    "symptoms": [],
    "supplements": [],
    "topics_system": [
      "饮食结构与膳食模式"
    ],
    "topic_group": "饮食结构与油脂选择",
    "source_file": "2026年07月04日_baoer.md",
    "id": "2026-07-04-37"
  },
  {
    "date": "2026-07-04",
    "question": "【群友分享】铁指标解读——转铁蛋白饱和度低但铁蛋白高",
    "answer": "铁：10.90（参考区间：10.60～36.70 μmol/L），不饱和铁结合力：52.6 ↑（参考区间：31.0～51.0 μmol/L），转铁蛋白：2.40（参考区间：2.00～4.00 g/L），转铁蛋白饱和度：17.2 ↓（参考区间：20.0～55.0 %），总铁结合力：63.5（参考区间：45.0～75.0 μmol/L），铁蛋白：520.9 ↑（参考区间：27.0～375.0 ng/mL），FT3：6.88 ↑（参考区间：2.76～6.45 pmol/L），FT4：21.74（参考区间：11.20～23.81 pmol/L），TSH：1.238（参考区间：0.350～5.100 mIU/L）。问：宁哥，这个铁代谢问题大吗？答：转铁蛋白饱和度低于20%是缺铁了。但是铁蛋白却高达520，说明有炎症。这不是饮食性缺铁，也不是铁过量。铁蛋白高加转铁蛋白饱和度低，两个指标放在一起，指向的是急性炎症——炎症导致铁被\"锁\"在储备库（铁蛋白）里，无法正常动员出来供身体使用，所以血清中的可利用铁（转铁蛋白饱和度）反而偏低。解决这个问题最好的办法就是解决炎症问题，不管是细菌、病毒感染，还是什么炎症灶，把它找出来，解决掉就好了。",
    "type": "横向互助",
    "symptoms": [
      "炎症"
    ],
    "supplements": [],
    "topics_system": [
      "血管血液与微循环",
      "免疫自免与过敏"
    ],
    "clinical_indicators": [
      "铁蛋白",
      "转铁蛋白饱和度",
      "转铁蛋白",
      "总铁结合力",
      "不饱和铁结合力",
      "游离三碘甲状腺原氨酸",
      "游离甲状腺素",
      "促甲状腺激素"
    ],
    "topic_group": "指标解读",
    "source_file": "2026年07月04日_baoer.md",
    "id": "2026-07-04-38"
  },
  {
    "date": "2026-07-04",
    "question": "【群友分享】婴儿低氧与抗氧化",
    "answer": "群友：听说婴儿是低氧状态，还在母体时候。但是那时候婴儿不产生低氧应激反应。生下来之后体内各种抗氧化剂才会大幅上升，维持一个平衡。这是不是说明氧气系统对人体来说不是必须的，可能氧化是有害的。黄老师评：这说明不了什么。没有氧气你无法产生90%以上的ATP，你就死了。主要的问题不是氧气，而是自由基过多。婴儿刚出生还喝母乳，里面的糖含量占比蛋白质和脂肪都高，你能说人类不应该生酮，应该吃高碳水高糖饮食吗？这只是一个过渡期，很短的时期，不代表全部。因为这个时候婴儿的肝脏还没有发育充分，糖异生还不能完全满足需求，所以才需要乳糖。",
    "type": "群友反馈",
    "symptoms": [],
    "supplements": [],
    "topics_system": [
      "氧化还原与抗氧化防御"
    ],
    "topic_group": "健康观念",
    "source_file": "2026年07月04日_baoer.md",
    "id": "2026-07-04-39"
  },
  {
    "date": "2026-07-04",
    "question": "【群友分享】血清指标解读——总蛋白低、胆固醇高",
    "answer": "血清总蛋白：64.7 ↓（参考区间：65-85 g/L），血清总胆固醇：7.41 ↑（参考区间：3-5.7 mmol/L），血清甘油三酯：0.91，血清高密度脂蛋白胆固醇：1.94 ↑（参考区间：1.03-1.55 mmol/L），血清低密度脂蛋白胆固醇：4.57 ↑（参考区间：1.89-4.21 mmol/L）。黄老师评：什么饮食？你吃肉太少。问：胆固醇高是吃肉少吗？黄老师：不是，你总蛋白低，所以我问你是不是吃肉少。如果是生酮饮食，胆固醇一般会升高，是正常现象，不是有害的。追问：我饭量总体少，一天就一顿饭，一顿饭都是以肉食为主。黄老师：第一，把盐吃够，每天最少10克盐。吃肉吃两口肉之后，建议你吃点盐酸甜菜碱。第二，把肉多吃一点。一天一顿的话，大多数人一定要把自己吃撑，不然长期可能营养不良。追问：我自从吃肉，胆固醇就一直居高不下，我总蛋白值低。多吃肉才能升蛋白是吗？我的甘油三酯低吗？盐酸甜菜碱起什么作用？黄老师：看看这些，你就明白了。[低碳后，体检指标怎么看](https://mp.weixin.qq.com/s/Per6kycbuZ810FPSDFo7mw)。盐酸甜菜碱是用来增加胃酸，帮助你消化肉的，提高肉的吸收能力，特别是年纪大的人更需要。多吃肉，摄入更多蛋白质，你的总蛋白肯定会升高。",
    "type": "群友反馈",
    "symptoms": [
      "高胆固醇"
    ],
    "supplements": [
      "海盐",
      "盐酸甜菜碱"
    ],
    "topics_system": [
      "饮食结构与膳食模式",
      "血管血液与微循环"
    ],
    "clinical_indicators": [
      "血清总蛋白",
      "总胆固醇",
      "甘油三酯",
      "高密度脂蛋白胆固醇",
      "低密度脂蛋白胆固醇"
    ],
    "topic_group": "指标解读",
    "dosage_info": [
      {
        "supplement": "海盐",
        "dosage": "每天最少10克盐",
        "timing": ""
      },
      {
        "supplement": "盐酸甜菜碱",
        "dosage": "吃两口肉之后吃点盐酸甜菜碱",
        "timing": "吃肉后"
      }
    ],
    "source_file": "2026年07月04日_baoer.md",
    "id": "2026-07-04-40"
  },
  {
    "date": "2026-07-04",
    "question": "甘氨酸与胶原蛋白——每天摄入10克甘氨酸",
    "answer": "黄老师分享：每天摄入10克甘氨酸，胶原蛋白合成量可能会增加高达250%。追问：甘氨酸有点甜，不敢吃这么多，会降酮么？那么甜，我担心出酮，促进胰岛素分泌。黄老师答：不会升多少血糖，甘氨酸是促进胰高血糖素分泌的，不是胰岛素。",
    "type": "Q&A",
    "symptoms": [],
    "supplements": [
      "甘氨酸",
      "胶原蛋白肽"
    ],
    "topics_system": [
      "运动五官与结缔组织"
    ],
    "topic_group": "胶原蛋白",
    "dosage_info": [
      {
        "supplement": "甘氨酸",
        "dosage": "每天10克",
        "timing": ""
      }
    ],
    "source_file": "2026年07月04日_baoer.md",
    "id": "2026-07-04-41"
  },
  {
    "date": "2026-07-04",
    "question": "VC对肠道菌群的作用",
    "answer": "黄老师分享：有益菌增加——双歧杆菌，每日500到1000毫克，丰度提升2到4倍；丁酸产生菌，丁酸盐产量增加30%到40%；乳杆菌，定植能力增强。有害菌减少——脱硫弧菌，每日1000毫克，4周后降低20%到30%；肠杆菌科，通过降低肠道pH抑制条件致病菌；拟杆菌，高剂量VC可减少，降低促炎因子释放。",
    "type": "Q&A",
    "symptoms": [],
    "supplements": [
      "维生素C"
    ],
    "topics_system": [
      "屏障消化与肠道"
    ],
    "topic_group": "维生素C与肠道",
    "source_file": "2026年07月04日_baoer.md",
    "id": "2026-07-04-42"
  },
  {
    "date": "2026-07-04",
    "question": "发烧与免疫力的关系",
    "answer": "黄老师分享：不发烧：先天性免疫好（第一道防线强），获得性免疫不确定（第二道防线不确定）。发烧且很快恢复：先天性免疫不好（第一道防线弱），获得性免疫好（第二道防线强）。发烧且迁延不愈：先天性免疫不好（第一道防线弱），获得性免疫也不好（第二道防线弱）。",
    "type": "Q&A",
    "symptoms": [
      "发热"
    ],
    "supplements": [],
    "topics_system": [
      "免疫自免与过敏"
    ],
    "topic_group": "免疫认知",
    "source_file": "2026年07月04日_baoer.md",
    "id": "2026-07-04-43"
  },
  {
    "date": "2026-07-04",
    "question": "复合维生素与新冠",
    "answer": "黄老师分享：[复合维生素与新冠](https://mp.weixin.qq.com/s/-1aXGBUjsPtWF4L6ei73Qg)",
    "type": "Q&A",
    "symptoms": [],
    "supplements": [],
    "topics_system": [
      "免疫自免与过敏"
    ],
    "topic_group": "新冠",
    "source_file": "2026年07月04日_baoer.md",
    "id": "2026-07-04-44"
  },
  {
    "date": "2026-07-04",
    "question": "肺结核与胆固醇——LDL是免疫护盾",
    "answer": "黄老师分享：背景事实：斯拉夫农奴社区肺结核发病率是贵族庄园的30到40倍。农奴几乎不吃肉，除了节日之外几乎不吃乳制品，极度缺乏动物脂肪和胆固醇来源。微观机理（LDL-免疫轴）：一、LDL是免疫护盾。LDL能够结合并灭活细菌产生的脂多糖/内毒素以及金黄色葡萄球菌的α-毒素，防止细胞因子风暴（Feingold & Grunfeld, 2011）。二、胆固醇与巨噬细胞。农奴极度缺乏动物脂肪（胆固醇来源），导致血清胆固醇水平过低。流行病学研究一致显示，低胆固醇水平与传染病（特别是呼吸道感染和肺结核）的高死亡率显著相关（Jacobs等，1992）。三、原材料短缺的连锁后果。缺乏胆固醇导致细胞膜构建原料不足，皮质醇（抗炎激素）合成受限，免疫系统如同没有弹药的士兵，无法有效抵抗感染。核心结论：LDL不是心血管疾病的单纯元凶，它在免疫防御中扮演关键角色。低的胆固醇水平，意味着免疫系统失去了重要的\"弹药\"和\"盾牌\"。",
    "type": "Q&A",
    "symptoms": [],
    "supplements": [],
    "topics_system": [
      "免疫自免与过敏",
      "血管血液与微循环"
    ],
    "topic_group": "胆固醇与免疫",
    "source_file": "2026年07月04日_baoer.md",
    "id": "2026-07-04-45"
  },
  {
    "date": "2026-07-04",
    "question": "植物油骗局：被隐藏35年的真相",
    "answer": "黄老师分享：1966年悉尼饮食心脏研究，458名心脏病患者，7年随访。用红花油（富含Omega-6）代替黄油的一组，死亡率反而更高：冠心病死亡率增加74%，心血管死亡率增加70%，全因死亡率增加62%。1978年只公布了部分数据，心血管和冠心病死亡数据被隐藏。直到2013年原始数据才被恢复，真相才曝光。机制：Omega-6在高温下氧化，产生有毒醛类（丙二醛、4-羟基壬烯醛），损伤血管，加速动脉粥样硬化。同样被压制的还有明尼苏达冠状动脉实验（9423人），结果一致：植物油降胆固醇，但增加死亡率，数据被藏了16年。安全替代：黄油、酥油、牛油、椰子油。特级初榨橄榄油只冷吃，不加热。",
    "type": "Q&A",
    "symptoms": [],
    "supplements": [],
    "topics_system": [
      "饮食结构与膳食模式",
      "血管血液与微循环"
    ],
    "topic_group": "饮食结构与油脂选择",
    "source_file": "2026年07月04日_baoer.md",
    "id": "2026-07-04-46"
  },
  {
    "date": "2026-07-04",
    "question": "生酮与胆固醇指标——LDL、ApoB对酮学没价值",
    "answer": "黄老师分享：生酮饮食会导致胆固醇（LDL-C）和载脂蛋白B（ApoB）显著升高，主流界认为这会增加动脉硬化风险。于是David Feldman等医生对100名生酮饮食者跟踪观察了一年（平均生酮饮食已经5.5年）。结果显示这些指标和动脉斑块发展无相关性，有些人的斑块还缩小了。LDL-C、ApoB并非评估血管风险的\"黄金标准\"，对我们酮学没有价值。",
    "type": "Q&A",
    "symptoms": [],
    "supplements": [],
    "topics_system": [
      "饮食结构与膳食模式",
      "血管血液与微循环"
    ],
    "topic_group": "生酮饮食",
    "source_file": "2026年07月04日_baoer.md",
    "id": "2026-07-04-47"
  },
  {
    "date": "2026-07-04",
    "question": "维生素C解毒重金属",
    "answer": "黄老师分享：[关于维生素C解毒重金属](https://mp.weixin.qq.com/s/YJewpauvqA4HsXETb4trRQ)",
    "type": "Q&A",
    "symptoms": [],
    "supplements": [
      "维生素C"
    ],
    "topics_system": [
      "解毒肝肾与排毒"
    ],
    "topic_group": "维生素C",
    "source_file": "2026年07月04日_baoer.md",
    "id": "2026-07-04-48"
  },
  {
    "date": "2026-07-04",
    "question": "生酮与糖异生",
    "answer": "黄老师分享：[关于生酮与糖异生](https://www.xiaohongshu.com/collection/item/6867aeb0018d000000000003?xhsshare=WeixinSession&appuid=5a93da1bdb2e6034cde5d8de&apptime=1783171272&share_id=1f6a53c4855f4c7caf59d650b0ad5d9f)",
    "type": "Q&A",
    "symptoms": [],
    "supplements": [],
    "topics_system": [
      "饮食结构与膳食模式",
      "能量线粒体与代谢"
    ],
    "topic_group": "生酮饮食",
    "source_file": "2026年07月04日_baoer.md",
    "id": "2026-07-04-49"
  },
  {
    "date": "2026-07-04",
    "question": "黄老师提醒：健康来源于饮食改变",
    "answer": "健康来源于【饮食改变】建议从低碳起步，向生酮甚至纯肉过渡（低碳→生酮→纯肉，越往后效果越好）。核心原则：多吃肉，少吃素：以红肉为主，尽量减少碳水和糖。选对油脂：不吃种子油，少吃植物油；多吃动物油脂（猪油、牛油、羊油、黄油、酥油）。避免以下食物：小麦、豆类、玉米、坚果、奶制品（黄油、酥油和偶尔自制的A2酸奶/羊酸奶除外）。少吃高风险植物：草酸高、凝集素高、多不饱和脂肪酸高、纤维高的植物。足量盐：每天10到15克，不要少油少盐。",
    "type": "Q&A",
    "symptoms": [],
    "supplements": [],
    "topics_system": [
      "饮食结构与膳食模式"
    ],
    "topic_group": "",
    "source_file": "2026年07月04日_baoer.md",
    "id": "2026-07-04-50"
  },
  {
    "date": "2026-07-05",
    "question": "牛骨髓牛棒骨中段属于脂肪吧？",
    "answer": "黄老师：非常好",
    "type": "Q&A",
    "symptoms": [],
    "supplements": [],
    "topics_system": [
      "饮食结构与膳食模式"
    ],
    "topic_group": "",
    "source_file": "2026年07月05日_baoer.md",
    "id": "2026-07-05-01"
  },
  {
    "date": "2026-07-05",
    "question": "【群友见证】坚持晒太阳改善记忆力，肤色更健康",
    "answer": "我坚持让老大白天光着身子晒太阳10分钟，没有晒黑，肤色看着就是很精神，健康。记忆力也有改善，之前学习记不住，现在好太多了。\n黄老师：是的，控制时间不容易黑的，是的，各项机能都会越来越好",
    "type": "群友反馈",
    "symptoms": [
      "记忆力差"
    ],
    "supplements": [],
    "topics_system": [
      "神经睡眠与脑雾",
      "物理干预与能量医学"
    ],
    "topic_group": "物理干预与光照",
    "source_file": "2026年07月05日_baoer.md",
    "id": "2026-07-05-02"
  },
  {
    "date": "2026-07-05",
    "question": "【群友见证】生酮后深睡时间提高，梦少了睡得沉",
    "answer": "提高了深睡时间，梦也少了，睡的比以前沉。生酮可以治疗神经指数紊乱，调节昼夜规律、交感神经和副交感神经。生酮后睡前一颗甘氨酸镁，基本无梦。",
    "type": "群友反馈",
    "symptoms": [
      "失眠",
      "睡眠质量差"
    ],
    "supplements": [
      "甘氨酸镁"
    ],
    "topics_system": [
      "神经睡眠与脑雾",
      "饮食结构与膳食模式"
    ],
    "topic_group": "",
    "source_file": "2026年07月05日_baoer.md",
    "id": "2026-07-05-03"
  },
  {
    "date": "2026-07-05",
    "question": "干眼症怎么办？",
    "answer": "黄老师：改变饮食+全面足量营养补充",
    "type": "Q&A",
    "symptoms": [
      "眼干"
    ],
    "supplements": [],
    "topics_system": [
      "运动五官与结缔组织"
    ],
    "topic_group": "",
    "source_file": "2026年07月05日_baoer.md",
    "id": "2026-07-05-04"
  },
  {
    "date": "2026-07-05",
    "question": "【群友见证】多吃脂肪不喝咖啡，皮肤变饱满了",
    "answer": "今天多吃了点脂肪，然后今天没有喝咖啡，我的皮肤又变饱满了。",
    "type": "群友反馈",
    "symptoms": [
      "皮肤干"
    ],
    "supplements": [],
    "topics_system": [
      "运动五官与结缔组织",
      "饮食结构与膳食模式"
    ],
    "topic_group": "",
    "source_file": "2026年07月05日_baoer.md",
    "id": "2026-07-05-05"
  },
  {
    "date": "2026-07-05",
    "question": "【群友见证】口腔溃疡用B2+VC+基础营养素一天愈合",
    "answer": "昨天嘴里长了2个溃疡，1200mg的B2，VC10克多，基础营养素1包，今天创面就基本愈合了。",
    "type": "群友反馈",
    "symptoms": [
      "口腔溃疡"
    ],
    "supplements": [
      "维生素C",
      "维生素B2",
      "基础全营养素"
    ],
    "topics_system": [
      "运动五官与结缔组织",
      "氧化还原与抗氧化防御"
    ],
    "topic_group": "",
    "source_file": "2026年07月05日_baoer.md",
    "id": "2026-07-05-06"
  },
  {
    "date": "2026-07-05",
    "question": "【群友分享】血脂指标及黄老师点评",
    "answer": "总胆固醇6.41，高密度1.15，低密度4.06，小而密低密度1.20，甘油三酯0.95\n黄老师评：多吃点动物脂肪、饱和脂肪，高密度太低",
    "type": "群友反馈",
    "symptoms": [
      "血脂高"
    ],
    "supplements": [],
    "topics_system": [
      "血管血液与微循环",
      "饮食结构与膳食模式"
    ],
    "clinical_indicators": [
      "总胆固醇",
      "高密度脂蛋白胆固醇",
      "低密度脂蛋白胆固醇",
      "甘油三酯"
    ],
    "topic_group": "",
    "source_file": "2026年07月05日_baoer.md",
    "id": "2026-07-05-07"
  },
  {
    "date": "2026-07-05",
    "question": "喝全营养素和VC后拉肚子，是VC还是献血的原因？",
    "answer": "黄老师：先不吃vc看看",
    "type": "Q&A",
    "symptoms": [
      "腹泻"
    ],
    "supplements": [
      "维生素C",
      "基础全营养素"
    ],
    "topics_system": [
      "屏障消化与肠道"
    ],
    "topic_group": "补剂适应与腹泻",
    "source_file": "2026年07月05日_baoer.md",
    "id": "2026-07-05-08"
  },
  {
    "date": "2026-07-05",
    "question": "白癜风吃VC会不会更白？",
    "answer": "黄老师：可以治疗白癜风。",
    "type": "Q&A",
    "symptoms": [
      "白癜风"
    ],
    "supplements": [
      "维生素C"
    ],
    "topics_system": [
      "免疫自免与过敏",
      "氧化还原与抗氧化防御"
    ],
    "topic_group": "",
    "source_file": "2026年07月05日_baoer.md",
    "id": "2026-07-05-09"
  },
  {
    "date": "2026-07-05",
    "question": "反流性食管炎烧心，盐水和盐酸甜菜碱还能继续吃吗？",
    "answer": "黄老师：多加盐，盐酸甜菜碱继续吃。这几天犯病了的话可以断食1-2天。",
    "type": "Q&A",
    "symptoms": [
      "反酸",
      "烧心"
    ],
    "supplements": [
      "海盐",
      "盐酸甜菜碱"
    ],
    "topics_system": [
      "屏障消化与肠道"
    ],
    "topic_group": "胃酸与消化",
    "source_file": "2026年07月05日_baoer.md",
    "id": "2026-07-05-10"
  },
  {
    "date": "2026-07-05",
    "question": "早上8点晒太阳30分钟还是黑了，怎么晒才合适？",
    "answer": "黄老师：10-11点晒正反面各5分钟",
    "type": "Q&A",
    "symptoms": [],
    "supplements": [],
    "topics_system": [
      "物理干预与能量医学"
    ],
    "topic_group": "物理干预与光照",
    "source_file": "2026年07月05日_baoer.md",
    "id": "2026-07-05-11"
  },
  {
    "date": "2026-07-05",
    "question": "大剂量VC加吃肉会不会有指标问题？网上说是谣言可信吗？",
    "answer": "群友：这玩意儿是不是谣言群里面不是还有很多人在执行这个吃法吗？你问他们呀。黄教主自己都在生酮纯肉加大剂量VC，你看他有没有问题。其实不用那么纠结，群里各种科普知识也很多，维生素C是干嘛的自己看看就行。可以自己去试试。",
    "type": "横向互助",
    "symptoms": [],
    "supplements": [
      "维生素C"
    ],
    "topics_system": [
      "氧化还原与抗氧化防御",
      "饮食结构与膳食模式"
    ],
    "topic_group": "",
    "source_file": "2026年07月05日_baoer.md",
    "id": "2026-07-05-12"
  },
  {
    "date": "2026-07-05",
    "question": "无水甜菜碱吃完发热刺挠是过敏吗？",
    "answer": "黄老师：过段时间就好了，建议烟酸和无水甜菜碱一起吃，分多次吃完，不然潮红会很厉害。",
    "type": "Q&A",
    "symptoms": [
      "皮肤痒"
    ],
    "supplements": [
      "无水甜菜碱",
      "烟酸"
    ],
    "topics_system": [
      "解毒肝肾与排毒"
    ],
    "topic_group": "补剂用法与搭配",
    "source_file": "2026年07月05日_baoer.md",
    "id": "2026-07-05-13"
  },
  {
    "date": "2026-07-05",
    "question": "一口闷五六克盐后脸肿了怎么办？",
    "answer": "黄老师：第一，盐不是这样吃的。盐是分散到一天当中逐步摄入的，不是一次性怼进去的。第二，一次性怼进去导致短期钠钾失衡，再加上平时可能钾没补够，就很容易肿。",
    "type": "Q&A",
    "symptoms": [
      "水肿"
    ],
    "supplements": [
      "海盐",
      "钾"
    ],
    "topics_system": [
      "血管血液与微循环"
    ],
    "topic_group": "盐与电解质",
    "source_file": "2026年07月05日_baoer.md",
    "id": "2026-07-05-14"
  },
  {
    "date": "2026-07-05",
    "question": "吃盐要多喝点水吗？会影响渗透压吗？",
    "answer": "黄老师：并不需要太多水。\n追问：不会影响渗透压吗？\n黄老师：身体会调节渗透压，没有那么脆弱。吃够了盐和电解质，你是不容易口渴的。",
    "type": "Q&A",
    "symptoms": [],
    "supplements": [
      "海盐"
    ],
    "topics_system": [
      "血管血液与微循环"
    ],
    "topic_group": "盐与电解质",
    "source_file": "2026年07月05日_baoer.md",
    "id": "2026-07-05-15"
  },
  {
    "date": "2026-07-05",
    "question": "甘氨酸硼有推荐的吗？",
    "answer": "黄老师：直接吃基础全营养素或微量元素粉或胶囊，里面都有。",
    "type": "Q&A",
    "symptoms": [],
    "supplements": [
      "基础全营养素"
    ],
    "topics_system": [
      "内分泌与激素调控"
    ],
    "topic_group": "",
    "source_file": "2026年07月05日_baoer.md",
    "id": "2026-07-05-16"
  },
  {
    "date": "2026-07-05",
    "question": "有单独卖甘氨酸硼吗？硼不够怎么办？",
    "answer": "黄老师：没有，不需要单独吃，一起补最好。\n追问：按我的需求硼还不够！吃多了其他又超标\n黄老师：协同一起吃才不容易超标，单独多补硼反而容易出问题。",
    "type": "Q&A",
    "symptoms": [],
    "supplements": [
      "基础全营养素"
    ],
    "topics_system": [
      "内分泌与激素调控"
    ],
    "topic_group": "",
    "source_file": "2026年07月05日_baoer.md",
    "id": "2026-07-05-17"
  },
  {
    "date": "2026-07-05",
    "question": "熊胆粉可以吃吗？",
    "answer": "黄老师：可以",
    "type": "Q&A",
    "symptoms": [],
    "supplements": [],
    "topics_system": [
      "解毒肝肾与排毒"
    ],
    "topic_group": "",
    "source_file": "2026年07月05日_baoer.md",
    "id": "2026-07-05-18"
  },
  {
    "date": "2026-07-05",
    "question": "棕榈油怎么样？",
    "answer": "黄老师：跟椰子油类似，不过VE很高",
    "type": "Q&A",
    "symptoms": [],
    "supplements": [],
    "topics_system": [
      "饮食结构与膳食模式"
    ],
    "topic_group": "",
    "source_file": "2026年07月05日_baoer.md",
    "id": "2026-07-05-19"
  },
  {
    "date": "2026-07-05",
    "question": "8岁孩子的营养素用量是成人的一半吗？",
    "answer": "黄老师：建议1/3~1/2",
    "type": "Q&A",
    "symptoms": [],
    "supplements": [
      "基础全营养素"
    ],
    "topics_system": [
      "其他/综合"
    ],
    "topic_group": "",
    "source_file": "2026年07月05日_baoer.md",
    "id": "2026-07-05-20"
  },
  {
    "date": "2026-07-05",
    "question": "补剂不放冰箱会坏吗？哪些必须冷藏？",
    "answer": "黄老师：可以放。不一定，三合一油、四合一油、九合一油肯定要放冰箱冷藏。单独的活性B族或DK最好也放冰箱冷藏。其他的密封好放阴凉处，问题不大。",
    "type": "Q&A",
    "symptoms": [],
    "supplements": [],
    "topics_system": [
      "其他/综合"
    ],
    "topic_group": "补剂用法与搭配",
    "source_file": "2026年07月05日_baoer.md",
    "id": "2026-07-05-21"
  },
  {
    "date": "2026-07-05",
    "question": "给家人推荐VC，只有泡腾粉会拉肚子吗？所有VC都会？",
    "answer": "黄老师：所有VC吃多了都会拉肚子。推荐VC泡腾粉，好喝。可以泡水弄成冰棍，早上下午晚上各啃几口。\n回：我家人每天一条vc不拉肚子\n黄老师：那就可以继续。",
    "type": "Q&A",
    "symptoms": [
      "腹泻"
    ],
    "supplements": [
      "维C泡腾粉",
      "维生素C"
    ],
    "topics_system": [
      "屏障消化与肠道",
      "氧化还原与抗氧化防御"
    ],
    "topic_group": "补剂适应与腹泻",
    "source_file": "2026年07月05日_baoer.md",
    "id": "2026-07-05-22"
  },
  {
    "date": "2026-07-05",
    "question": "补剂没放冰箱放柜子可以吧？",
    "answer": "黄老师：密封好，放阴凉处，防潮做好就行。",
    "type": "Q&A",
    "symptoms": [],
    "supplements": [],
    "topics_system": [
      "其他/综合"
    ],
    "topic_group": "",
    "source_file": "2026年07月05日_baoer.md",
    "id": "2026-07-05-23"
  },
  {
    "date": "2026-07-05",
    "question": "第一次吃全营养素和VC泡腾粉，两种可以一起吃吗？怎么吃？",
    "answer": "黄老师：先吃基础全营养素，从半包慢慢加到两包不拉肚子，再加入VC泡腾粉从半包加到一包。长期保健剂量是一天两包基础全营养素或45粒胶囊加一包VC泡腾粉。过程中可加岩藻多糖帮助适应。",
    "type": "Q&A",
    "symptoms": [],
    "supplements": [
      "基础全营养素",
      "维C泡腾粉",
      "岩藻多糖"
    ],
    "topics_system": [
      "屏障消化与肠道"
    ],
    "topic_group": "补剂适应与腹泻",
    "source_file": "2026年07月05日_baoer.md",
    "id": "2026-07-05-24",
    "dosage_info": [
      {
        "supplement": "基础全营养素",
        "dosage": "先吃全素，从半包渐加到两包不拉肚子",
        "timing": "早上下午晚上各一次"
      },
      {
        "supplement": "维C泡腾粉",
        "dosage": "适应全素后从半包渐加到一包",
        "timing": ""
      }
    ]
  },
  {
    "date": "2026-07-05",
    "question": "甜梦粉剂冲水喝什么味道？",
    "answer": "小助理答：口感一般般，对味道要求高的不建议，如果能包糯米纸的话也可以。建议胶囊。",
    "type": "Q&A",
    "symptoms": [],
    "supplements": [],
    "topics_system": [
      "神经睡眠与脑雾"
    ],
    "topic_group": "",
    "source_file": "2026年07月05日_baoer.md",
    "id": "2026-07-05-25"
  },
  {
    "date": "2026-07-05",
    "question": "B族和Q10一天吃几粒？",
    "answer": "小助理答：活性B族保健剂量一天1克或两粒胶囊，分两次。Q10胶囊保健剂量一天0.2-0.4克或两粒胶囊，分两次，都随餐。",
    "type": "Q&A",
    "symptoms": [],
    "supplements": [
      "活性B族",
      "辅酶Q10"
    ],
    "topics_system": [
      "能量线粒体与代谢"
    ],
    "topic_group": "补剂用法与搭配",
    "source_file": "2026年07月05日_baoer.md",
    "id": "2026-07-05-26",
    "dosage_info": [
      {
        "supplement": "活性B族",
        "dosage": "保健一天1克或2粒胶囊",
        "timing": "分两次随餐"
      },
      {
        "supplement": "辅酶Q10",
        "dosage": "保健一天0.2-0.4克或2粒胶囊",
        "timing": "分两次随餐"
      }
    ]
  },
  {
    "date": "2026-07-05",
    "question": "无水甜菜碱吃多少合适？怎么吃？",
    "answer": "黄老师：一般3-5克。不用分批，全部倒在一起泡水喝，从早到晚慢慢喝就完了。\n追问：烟酸可以吃到1克吗？\n黄老师：可以，只要受得了潮红就行。\n追问：味道怪怪的喝不进去怎么办？\n黄老师：实在受不了就分批吃。",
    "type": "Q&A",
    "symptoms": [],
    "supplements": [
      "无水甜菜碱",
      "烟酸"
    ],
    "topics_system": [
      "解毒肝肾与排毒"
    ],
    "topic_group": "补剂用法与搭配",
    "source_file": "2026年07月05日_baoer.md",
    "id": "2026-07-05-27",
    "dosage_info": [
      {
        "supplement": "无水甜菜碱",
        "dosage": "一般3-5克；全部泡水从早到晚慢慢喝",
        "timing": ""
      },
      {
        "supplement": "烟酸",
        "dosage": "可以吃到1克",
        "timing": ""
      }
    ]
  },
  {
    "date": "2026-07-05",
    "question": "烟酸不是胶囊怎么吃？直接冲水？",
    "answer": "小助理答：包糯米纸或自己灌胶囊或包埋都可以，一天1克分两次随餐。\n追问：可以直接冲水喝吗？包埋是怎么搞的？\n小助理答：可以冲水喝，我最开始就是活性B族粉末加甘氨酸镁粉末泡水喝了几个月。\n包埋教程：[包埋链接](https://mp.weixin.qq.com/s/-yTmPAjM1Dun62hIyCR_mA)",
    "type": "Q&A",
    "symptoms": [],
    "supplements": [
      "烟酸"
    ],
    "topics_system": [
      "其他/综合"
    ],
    "topic_group": "补剂用法与搭配",
    "source_file": "2026年07月05日_baoer.md",
    "id": "2026-07-05-28",
    "dosage_info": [
      {
        "supplement": "烟酸",
        "dosage": "一天1克分两次随餐；包糯米纸/灌胶囊/包埋/直接冲水",
        "timing": "分两次随餐"
      }
    ]
  },
  {
    "date": "2026-07-05",
    "question": "鲍林粉和基础全营养素有什么区别？",
    "answer": "小助理答：与基础全营养素的差异在于微量元素和B族。",
    "type": "Q&A",
    "symptoms": [],
    "supplements": [
      "基础全营养素"
    ],
    "topics_system": [
      "其他/综合"
    ],
    "topic_group": "补剂用法与搭配",
    "source_file": "2026年07月05日_baoer.md",
    "id": "2026-07-05-29"
  },
  {
    "date": "2026-07-05",
    "question": "VC电解质泡水喝好还是包埋好？",
    "answer": "小助理答：店里的这两个都可以不用包埋。",
    "type": "Q&A",
    "symptoms": [],
    "supplements": [
      "维生素C"
    ],
    "topics_system": [
      "氧化还原与抗氧化防御"
    ],
    "topic_group": "补剂用法与搭配",
    "source_file": "2026年07月05日_baoer.md",
    "id": "2026-07-05-30"
  },
  {
    "date": "2026-07-05",
    "question": "有了基础全营养素还需要额外加无水甜菜碱吗？",
    "answer": "小助理答：保健不需要额外加。\n黄老师：看你需求，如果有额外加了1克以上的烟酸，最好加上2倍的无水甜菜碱。",
    "type": "Q&A",
    "symptoms": [],
    "supplements": [
      "基础全营养素",
      "无水甜菜碱",
      "烟酸"
    ],
    "topics_system": [
      "解毒肝肾与排毒"
    ],
    "topic_group": "补剂用法与搭配",
    "source_file": "2026年07月05日_baoer.md",
    "id": "2026-07-05-31"
  },
  {
    "date": "2026-07-05",
    "question": "【黄老师分享】血管卫士——糖萼文章",
    "answer": "[血管卫士——糖萼](https://mp.weixin.qq.com/s/pmhyGQs4-FlTJwRiYAd4Qg)",
    "type": "Q&A",
    "symptoms": [],
    "supplements": [],
    "topics_system": [
      "血管血液与微循环"
    ],
    "topic_group": "",
    "source_file": "2026年07月05日_baoer.md",
    "id": "2026-07-05-32"
  },
  {
    "date": "2026-07-05",
    "question": "【群友推荐】炖月牙骨的锅具分享",
    "answer": "昨天刚炖了一斤月牙骨，90度24小时炖化。\n锅：[六松智能电饭锅](https://e.tb.cn/h.SRcqXB5YCnGnGAv)\n内胆：[不锈钢316内胆](https://e.tb.cn/h.SiTj4tx0qgnautm)",
    "type": "群友反馈",
    "symptoms": [],
    "supplements": [],
    "topics_system": [
      "饮食结构与膳食模式"
    ],
    "topic_group": "",
    "source_file": "2026年07月05日_baoer.md",
    "id": "2026-07-05-33"
  },
  {
    "date": "2026-07-05",
    "question": "【群友分享】关于梦的科普",
    "answer": "我们每个人每天都要做梦，没有不做梦的。区别在于大脑记住了梦和没有记住。睡眠要经历好几个周期，做梦发生在其中某一个周期。如果你早上醒来刚好在这个周期就能记住做了梦，否则就以为没做梦。",
    "type": "群友反馈",
    "symptoms": [],
    "supplements": [],
    "topics_system": [
      "神经睡眠与脑雾"
    ],
    "topic_group": "",
    "source_file": "2026年07月05日_baoer.md",
    "id": "2026-07-05-34"
  },
  {
    "date": "2026-07-05",
    "question": "【群友分享】睡眠APP检测的提醒",
    "answer": "睡眠APP仅供参考，不要太在意。这些APP在深睡浅睡上误判非常大，包括手环。有的功能还是可以，比如提醒心跳心率不对，经常提醒就可以去医院查一查。",
    "type": "群友反馈",
    "symptoms": [],
    "supplements": [],
    "topics_system": [
      "神经睡眠与脑雾"
    ],
    "topic_group": "",
    "source_file": "2026年07月05日_baoer.md",
    "id": "2026-07-05-35"
  }
]